<?xml version="1.0" encoding="UTF-8"?>
<tns:dBEAR xmlns:tns="http://www.flancer64.com/dBEAR/Schema" xmlns:xsi="http://www.w3.org/2001/XMLSchema-instance"
	xsi:schemaLocation="http://www.flancer64.com/dBEAR/Schema ../../xsd/ded_1.0.0.xsd ">
	<tns:namespaces>
		<tns:namespace id="flancer32.dbear.sample">
			<tns:entities>
				<tns:entity id="AuthType">
					<tns:comment>Authentication type can be used in the current application.</tns:comment>
					<tns:attributes>
						<tns:attribute id="Value">
							<tns:type>
								<tns:text>
									<tns:length>255</tns:length>
								</tns:text>
							</tns:type>
						</tns:attribute>
					</tns:attributes>
				</tns:entity>
			</tns:entities>
			<tns:relations>
				<tns:relation id="Person_AuthType">
					<tns:refs>
						<tns:entityRef>
							<tns:namespace>flancer32.dbear.sample</tns:namespace>
							<tns:name>AuthType</tns:name>
						</tns:entityRef>
						<tns:entityRef>
							<tns:namespace>flancer32.dbear.sample</tns:namespace>
							<tns:name>Person</tns:name>
						</tns:entityRef>
					</tns:refs>
				</tns:relation>
			</tns:relations>
		</tns:namespace>
	</tns:namespaces>
</tns:dBEAR>
